Metadata-Version: 1.0
Name: pypipackageexamplejortega
Version: 0.0.1
Summary: Paquete de prueba
Home-page: https://github.com/JavierOrtegaFP/pypipackageexamplejortega
Author: Javier Ortega
Author-email: UNKNOWN
License: MIT
Platform: UNKNOWN
